[
    {
        "content": "<p>I'm not sure the best place to direct the question, and thought this was as good a place to start as any.  I received a 'spam' PM with a job posting. AFAICT there is no process for reporting a message or a user.  Is there one I missed somewhere?  Tagging people who may know the answer: <span class=\"user-mention\" data-user-id=\"191316\">@Grahame Grieve</span> <span class=\"user-mention\" data-user-id=\"191315\">@Josh Mandel</span> .  Thanks!</p>",
        "id": 219540213,
        "sender_full_name": "Gino Canessa",
        "timestamp": 1607637826
    },
    {
        "content": "<p>Just came here to say the same thing!</p>",
        "id": 219543230,
        "sender_full_name": "Josh Mandel",
        "timestamp": 1607639394
    },
    {
        "content": "<p>We need a policy and process to deal with this.</p>",
        "id": 219543390,
        "sender_full_name": "Josh Mandel",
        "timestamp": 1607639489
    },
    {
        "content": "<p>Looking at current policy I see:</p>\n<ul>\n<li><a href=\"https://confluence.hl7.org/display/FHIR/FHIR+Code+of+Conduct\">https://confluence.hl7.org/display/FHIR/FHIR+Code+of+Conduct</a></li>\n<li><a href=\"https://confluence.hl7.org/display/FHIR/Chat.fhir.org+Community+Expectations\">https://confluence.hl7.org/display/FHIR/Chat.fhir.org+Community+Expectations</a></li>\n</ul>\n<p>Though <a href=\"https://chat.fhir.org\">https://chat.fhir.org</a> links to an <a href=\"https://wiki.hl7.org/index.php?title=Chat.fhir.org_community_expectations#Announcements\">outdated wiki page</a> in the \"before joining\" section:</p>\n<p><a href=\"/user_uploads/10155/Vlw8aBAOU0TXMihcjzCvy0iY/image.png\">image.png</a></p>\n<div class=\"message_inline_image\"><a href=\"/user_uploads/10155/Vlw8aBAOU0TXMihcjzCvy0iY/image.png\" title=\"image.png\"><img src=\"/user_uploads/10155/Vlw8aBAOU0TXMihcjzCvy0iY/image.png\"></a></div>",
        "id": 219543540,
        "sender_full_name": "Josh Mandel",
        "timestamp": 1607639558
    },
    {
        "content": "<p>Now I feel left out. <span aria-label=\"cry\" class=\"emoji emoji-1f622\" role=\"img\" title=\"cry\">:cry:</span></p>",
        "id": 219543593,
        "sender_full_name": "Elliot Silver",
        "timestamp": 1607639593
    },
    {
        "content": "<p>The code of conduct and community expectations don't obviously rule out this kind of spammy behavior; not that additional language would <em>prevent</em> it, but we should at least be clear (and when we ban people, we can tie it back to violation of specifics).</p>",
        "id": 219543706,
        "sender_full_name": "Josh Mandel",
        "timestamp": 1607639649
    },
    {
        "content": "<p>I've already punted one user today for doing that.  (Jim someone).  If you've received from someone else, let me know.</p>",
        "id": 219544506,
        "sender_full_name": "Lloyd McKenzie",
        "timestamp": 1607640219
    },
    {
        "content": "<p><span class=\"user-mention silent\" data-user-id=\"191380\">Elliot Silver</span> <a href=\"#narrow/stream/179238-Zulip/topic/Sad.20Question/near/219543593\">said</a>:</p>\n<blockquote>\n<p>Now I feel left out. <span aria-label=\"cry\" class=\"emoji emoji-1f622\" role=\"img\" title=\"cry\">:cry:</span></p>\n</blockquote>\n<p>You need to add \"Spam Me\" to your name field!</p>",
        "id": 219545256,
        "sender_full_name": "Dave deBronkart",
        "timestamp": 1607640693
    },
    {
        "content": "<p><span class=\"user-mention silent\" data-user-id=\"191320\">Lloyd McKenzie</span> <a href=\"#narrow/stream/179238-Zulip/topic/Sad.20Question/near/219544506\">said</a>:</p>\n<blockquote>\n<p>I've already punted one user today for doing that.  (Jim someone).  If you've received from someone else, let me know.</p>\n</blockquote>\n<p>That's the one - lol @ not tagging you since I've been bothering you all week with publication stuff  =)</p>",
        "id": 219546855,
        "sender_full_name": "Gino Canessa",
        "timestamp": 1607641752
    },
    {
        "content": "<p><span class=\"user-mention\" data-user-id=\"191315\">@Josh Mandel</span> I think Zulip has some ongoing work on making it possible to restrict private messages for new community members, which might help prevent this sort of thing.  <a href=\"https://zulip.com/help/restrict-private-messages\">https://zulip.com/help/restrict-private-messages</a> has details, though the current setting options don't allow the type of option you might want (E.g. preventing new users from using PMs for the first 10 days, with the error linking to the community standards).</p>",
        "id": 223585942,
        "sender_full_name": "Tim Abbott",
        "timestamp": 1611271823
    }
]