[
    {
        "content": "<p>ajuliansr <a href=\"https://github.com/HL7/fhircast-docs/commit/a87ed22ad28a\">pushed</a> 1 commit to branch 20220330-package-list.</p>\n<ul>\n<li>pinging away at the packaglist (<a href=\"https://github.com/HL7/fhircast-docs/commit/a87ed22ad28adc43c4980c4ccfc605fcb4e9894e\">a87ed22</a>)</li>\n</ul>",
        "id": 277185625,
        "sender_full_name": "Github Notifications (FHIRcast)",
        "timestamp": 1648664134
    },
    {
        "content": "<p>ajuliansr <a href=\"https://github.com/HL7/fhircast-docs/compare/a87ed22ad28a...2d99dd07c614\">pushed</a> 1 commit to branch 20220330-package-list.</p>\n<ul>\n<li>Update package-list (<a href=\"https://github.com/HL7/fhircast-docs/commit/2d99dd07c6149dc4f92b1a94177e8bb77b6e5383\">2d99dd0</a>)</li>\n</ul>",
        "id": 277185981,
        "sender_full_name": "Github Notifications (FHIRcast)",
        "timestamp": 1648664299
    },
    {
        "content": "<p>ajuliansr <a href=\"https://github.com/HL7/fhircast-docs/compare/2d99dd07c614...359e105758c8\">pushed</a> 1 commit to branch 20220330-package-list.</p>\n<ul>\n<li>Update package-list.json (<a href=\"https://github.com/HL7/fhircast-docs/commit/359e105758c83cfe9e0702d6d65c50963f7ad407\">359e105</a>)</li>\n</ul>",
        "id": 277187204,
        "sender_full_name": "Github Notifications (FHIRcast)",
        "timestamp": 1648664857
    },
    {
        "content": "<p>ajuliansr <a href=\"https://github.com/HL7/fhircast-docs/compare/359e105758c8...c0cc7b3a0586\">pushed</a> 1 commit to branch 20220330-package-list.</p>\n<ul>\n<li>Update package-list.json (<a href=\"https://github.com/HL7/fhircast-docs/commit/c0cc7b3a058681e9455dfbc1862940a44a543564\">c0cc7b3</a>)</li>\n</ul>",
        "id": 277188497,
        "sender_full_name": "Github Notifications (FHIRcast)",
        "timestamp": 1648665408
    },
    {
        "content": "<p>ajuliansr <a href=\"https://github.com/HL7/fhircast-docs/compare/c0cc7b3a0586...4453c6275ddb\">pushed</a> 1 commit to branch 20220330-package-list.</p>\n<ul>\n<li>Update package-list.json (<a href=\"https://github.com/HL7/fhircast-docs/commit/4453c6275ddb07b96b0c507f7d687e4290814fec\">4453c62</a>)</li>\n</ul>",
        "id": 277189523,
        "sender_full_name": "Github Notifications (FHIRcast)",
        "timestamp": 1648665891
    },
    {
        "content": "<p>ajuliansr <a href=\"https://github.com/HL7/fhircast-docs/compare/4453c6275ddb...636612ac958c\">pushed</a> 1 commit to branch 20220330-package-list.</p>\n<ul>\n<li>Update package-list.json (<a href=\"https://github.com/HL7/fhircast-docs/commit/636612ac958cba0a40f82eef68c7e1d54d19bac6\">636612a</a>)</li>\n</ul>",
        "id": 277190674,
        "sender_full_name": "Github Notifications (FHIRcast)",
        "timestamp": 1648666408
    },
    {
        "content": "<p>ajuliansr <a href=\"https://github.com/HL7/fhircast-docs/compare/636612ac958c...85e43d75dc57\">pushed</a> 1 commit to branch 20220330-package-list.</p>\n<ul>\n<li>Update package-list.json (<a href=\"https://github.com/HL7/fhircast-docs/commit/85e43d75dc57cd6940950d518d70e4ec264dd5cb\">85e43d7</a>)</li>\n</ul>",
        "id": 277191194,
        "sender_full_name": "Github Notifications (FHIRcast)",
        "timestamp": 1648666663
    },
    {
        "content": "<p>ajuliansr <a href=\"https://github.com/HL7/fhircast-docs/compare/85e43d75dc57...b2acd5b47529\">pushed</a> 1 commit to branch 20220330-package-list.</p>\n<ul>\n<li>Changed ID back to original 14:02 (<a href=\"https://github.com/HL7/fhircast-docs/commit/b2acd5b47529819415bac43edc6a54ef03adde56\">b2acd5b</a>)</li>\n</ul>",
        "id": 277191846,
        "sender_full_name": "Github Notifications (FHIRcast)",
        "timestamp": 1648666941
    },
    {
        "content": "<p>ajuliansr <a href=\"https://github.com/HL7/fhircast-docs/compare/b2acd5b47529...7835c73276d1\">pushed</a> 1 commit to branch 20220330-package-list.</p>\n<ul>\n<li>update package-list.json 14:06 (<a href=\"https://github.com/HL7/fhircast-docs/commit/7835c73276d1fa083212429f254c93b52628bb8a\">7835c73</a>)</li>\n</ul>",
        "id": 277192299,
        "sender_full_name": "Github Notifications (FHIRcast)",
        "timestamp": 1648667173
    },
    {
        "content": "<p>ajuliansr <a href=\"https://github.com/HL7/fhircast-docs/compare/7835c73276d1...89a985814d02\">pushed</a> 1 commit to branch 20220330-package-list.</p>\n<ul>\n<li>Update FHIR-fhircast.xml  (<a href=\"https://github.com/HL7/fhircast-docs/commit/89a985814d02d78ce86c73e87c438b11c5681a5d\">89a9858</a>)</li>\n</ul>",
        "id": 277194719,
        "sender_full_name": "Github Notifications (FHIRcast)",
        "timestamp": 1648668507
    },
    {
        "content": "<p>ajuliansr <a href=\"https://github.com/HL7/fhircast-docs/compare/89a985814d02...d7a23c05cdb8\">pushed</a> 1 commit to branch 20220330-package-list.</p>\n<ul>\n<li>Update package-list.json (<a href=\"https://github.com/HL7/fhircast-docs/commit/d7a23c05cdb81ecd3767548b316ea9d68c25806d\">d7a23c0</a>)</li>\n</ul>",
        "id": 277195419,
        "sender_full_name": "Github Notifications (FHIRcast)",
        "timestamp": 1648668914
    },
    {
        "content": "<p>ajuliansr <a href=\"https://github.com/HL7/fhircast-docs/compare/d7a23c05cdb8...454c86748ea3\">pushed</a> 1 commit to branch 20220330-package-list.</p>\n<ul>\n<li>Update package-list.json  (<a href=\"https://github.com/HL7/fhircast-docs/commit/454c86748ea3ca3b2015b47c2df06f9c876ab831\">454c867</a>)</li>\n</ul>",
        "id": 277195741,
        "sender_full_name": "Github Notifications (FHIRcast)",
        "timestamp": 1648669085
    },
    {
        "content": "<p>ajuliansr <a href=\"https://github.com/HL7/fhircast-docs/compare/454c86748ea3...bfc410fd1362\">pushed</a> 1 commit to branch 20220330-package-list.</p>\n<ul>\n<li>Update package-list.json (<a href=\"https://github.com/HL7/fhircast-docs/commit/bfc410fd13625ab0e32166e82487861259bcc143\">bfc410f</a>)</li>\n</ul>",
        "id": 277197746,
        "sender_full_name": "Github Notifications (FHIRcast)",
        "timestamp": 1648670392
    },
    {
        "content": "<p>ajuliansr <a href=\"https://github.com/HL7/fhircast-docs/compare/bfc410fd1362...817d427be753\">pushed</a> 1 commit to branch 20220330-package-list.</p>\n<ul>\n<li>Update package-list.json (<a href=\"https://github.com/HL7/fhircast-docs/commit/817d427be753a9b13be61afe3287bd3e49937bc4\">817d427</a>)</li>\n</ul>",
        "id": 277198265,
        "sender_full_name": "Github Notifications (FHIRcast)",
        "timestamp": 1648670687
    },
    {
        "content": "<p>ajuliansr <a href=\"https://github.com/HL7/fhircast-docs/compare/817d427be753...000000000000\">deleted</a> the branch 20220330-package-list.</p>",
        "id": 277204435,
        "sender_full_name": "Github Notifications (FHIRcast)",
        "timestamp": 1648674699
    }
]