[
    {
        "content": "<p>Hi all, please feel free to contribute/edit the following list: <a href=\"http://wiki.hl7.org/index.php?title=National_FHIR_Projects\" target=\"_blank\" title=\"http://wiki.hl7.org/index.php?title=National_FHIR_Projects\">http://wiki.hl7.org/index.php?title=National_FHIR_Projects</a></p>",
        "id": 153928318,
        "sender_full_name": "Simone Heckmann",
        "timestamp": 1515610773
    },
    {
        "content": "<blockquote>\n<p>Hi all, please feel free to contribute/edit the following list: <a href=\"http://wiki.hl7.org/index.php?title=National_FHIR_Projects\" target=\"_blank\" title=\"http://wiki.hl7.org/index.php?title=National_FHIR_Projects\">http://wiki.hl7.org/index.php?title=National_FHIR_Projects</a></p>\n</blockquote>\n<p>Sorry for the late reply, is your request for any kind of FHIR project in Italy or for nation-wide FHIR projects ?</p>",
        "id": 153933141,
        "sender_full_name": "Giorgio Cangioli",
        "timestamp": 1517267235
    },
    {
        "content": "<p>... forget my question ...it was indicated in the wiki page...<br>\nNo Natioanl projects; I can check for regional ones and I let you know.</p>",
        "id": 153933143,
        "sender_full_name": "Giorgio Cangioli",
        "timestamp": 1517267458
    },
    {
        "content": "<p>Thanks for asking</p>",
        "id": 153933144,
        "sender_full_name": "Giorgio Cangioli",
        "timestamp": 1517267469
    }
]