[
    {
        "content": "<p>In <a href=\"http://Consent.provision.actor\">Consent.provision.actor</a>, both role and reference are required attributes.  What is the best way to express that a provision relates to all current and future owners of a particular role, i.e. that the role is the only criterion?  I am not very happy with fake references like <br>\n    \"actor\": [ {<br>\n      \"role\": {<br>\n        \"coding\": [ {<br>\n          \"system\": \"urn:oid:2.16.756.5.30.1.127.3.10.6\",<br>\n          \"code\": \"HCP\",<br>\n          \"display\": \"Healthcare Practitioner\"<br>\n        } ]<br>\n      },<br>\n      \"reference\": {<br>\n        \"display\": \"all\"<br>\n      }<br>\n    } ],</p>",
        "id": 251705094,
        "sender_full_name": "Dmytro Rud",
        "timestamp": 1630584942
    },
    {
        "content": "<p>I personally think that is a bug in the Consent resource. You should be able to identify actor by functional role code, structural role code, or any of the types of references... OR... not and...   Can you submit a Change Request?</p>",
        "id": 251725184,
        "sender_full_name": "John Moehrke",
        "timestamp": 1630593260
    },
    {
        "content": "<p>But, given this model, I think you likely have the best possible hack.</p>",
        "id": 251725252,
        "sender_full_name": "John Moehrke",
        "timestamp": 1630593286
    },
    {
        "content": "<p><span class=\"user-mention\" data-user-id=\"192587\">@David Pyke</span></p>",
        "id": 251737253,
        "sender_full_name": "Lloyd McKenzie",
        "timestamp": 1630597849
    },
    {
        "content": "<p>We have made the change for R5 that the role is no longer required and the role set is ParticipationRoleType<br>\nA reference is required, I'm not sure if PractitionerRole is not what you're looking for.  Any Actor assigned that PractitionerRole would meet the provision requirements.  For R4, setting the .provision.role to the closest and then setting provision.reference to a PractitionerRole should meet your use case, as I see it above.</p>",
        "id": 251738743,
        "sender_full_name": "David Pyke",
        "timestamp": 1630598355
    },
    {
        "content": "<p>except that <span class=\"user-mention\" data-user-id=\"191870\">@Dmytro Rud</span> wants to specify the role, but NOT the reference.</p>",
        "id": 251777494,
        "sender_full_name": "John Moehrke",
        "timestamp": 1630612886
    },
    {
        "content": "<p>a very reasonable thing. I might say the most likely need.</p>",
        "id": 251777553,
        "sender_full_name": "John Moehrke",
        "timestamp": 1630612909
    },
    {
        "content": "<p>such as.. I don't want anyone with the role of Pastor viewing my data</p>",
        "id": 251777949,
        "sender_full_name": "John Moehrke",
        "timestamp": 1630613044
    },
    {
        "content": "<p>Change Request submitted: <a href=\"https://jira.hl7.org/browse/FHIR-33384\">https://jira.hl7.org/browse/FHIR-33384</a></p>",
        "id": 251881412,
        "sender_full_name": "Dmytro Rud",
        "timestamp": 1630676392
    }
]