[
    {
        "content": "<p>Hi everyone<br>\nHow present ethnic of person in fhir. I fould some things like Patient extensions (ex: religion, nationality,..) but I'm not found ethnic</p>",
        "id": 181834356,
        "sender_full_name": "Dongtu",
        "timestamp": 1574696885
    },
    {
        "content": "<p>That is a US specific concept that will not be found in an international standard. See US-Core <a href=\"https://www.hl7.org/fhir/us/core/StructureDefinition-us-core-patient.html\" target=\"_blank\" title=\"https://www.hl7.org/fhir/us/core/StructureDefinition-us-core-patient.html\">https://www.hl7.org/fhir/us/core/StructureDefinition-us-core-patient.html</a></p>",
        "id": 181834571,
        "sender_full_name": "John Moehrke",
        "timestamp": 1574697037
    },
    {
        "content": "<p><span class=\"user-mention\" data-user-id=\"230970\">@Dongtu</span> is from Vietnam, where there's also ethnicity though the meaning and value set is very different. When I was there we proposed this as a vietnamese national extension. You should ask on the <a class=\"stream\" data-stream-id=\"179246\" href=\"/#narrow/stream/179246-vi.E1.BB.87tnam\">#việtnam</a> extension (btw, I will be there in April for an AEHIN... )</p>",
        "id": 181836539,
        "sender_full_name": "Grahame Grieve",
        "timestamp": 1574698240
    },
    {
        "content": "<p>ah: <a href=\"http://build.fhir.org/ig/grahamegrieve/vietnam-poc/extensions.html\" target=\"_blank\" title=\"http://build.fhir.org/ig/grahamegrieve/vietnam-poc/extensions.html\">http://build.fhir.org/ig/grahamegrieve/vietnam-poc/extensions.html</a></p>",
        "id": 181836593,
        "sender_full_name": "Grahame Grieve",
        "timestamp": 1574698285
    },
    {
        "content": "<p>Thanks <span class=\"user-mention\" data-user-id=\"191316\">@Grahame Grieve</span>  see you in April</p>",
        "id": 181837411,
        "sender_full_name": "Dongtu",
        "timestamp": 1574698782
    }
]