[
    {
        "content": "<p>The highlighted term shown below does not make sense to me - can anyone explain what it is?</p>\n<p><a href=\"/user_uploads/10155/YfcsmzMntsp3PGE-_YoF0tKv/image.png\">image.png</a></p>\n<div class=\"message_inline_image\"><a href=\"/user_uploads/10155/YfcsmzMntsp3PGE-_YoF0tKv/image.png\" title=\"image.png\"><img src=\"/user_uploads/10155/YfcsmzMntsp3PGE-_YoF0tKv/image.png\"></a></div>",
        "id": 251271952,
        "sender_full_name": "Richard Kavanagh",
        "timestamp": 1630347845
    },
    {
        "content": "<p>If had to make a guess, \"practitioner's office\". But somewhere along the line the ' went through a ASCII/UTF-8/UTF-16/ASCII/xxxx shift incorrectly.</p>",
        "id": 251272708,
        "sender_full_name": "Daniel Venton",
        "timestamp": 1630348170
    },
    {
        "content": "<p>the HL7 terminology content has been through several rounds of mangling, and I'm still chasing down character encoding issues like that. please make a task to fix it</p>",
        "id": 251275287,
        "sender_full_name": "Grahame Grieve",
        "timestamp": 1630349192
    }
]