[
    {
        "content": "<p><span class=\"user-mention\" data-user-id=\"191316\">@Grahame Grieve</span> <span class=\"user-mention\" data-user-id=\"191319\">@James Agnew</span>  ?</p>",
        "id": 198992275,
        "sender_full_name": "Simone Heckmann",
        "timestamp": 1590652429
    },
    {
        "content": "<p>I get <code>502 Bad Gateway</code></p>",
        "id": 198992323,
        "sender_full_name": "Simone Heckmann",
        "timestamp": 1590652451
    },
    {
        "content": "<p>Not sure who to notify about this but it looks like <a href=\"http://hapi.fhir.org/\">http://hapi.fhir.org/</a> is down, im getting 503's on all endpoints</p>",
        "id": 202702569,
        "sender_full_name": "Job Schipper",
        "timestamp": 1593703193
    },
    {
        "content": "<p><span class=\"user-mention\" data-user-id=\"191319\">@James Agnew</span></p>",
        "id": 202703252,
        "sender_full_name": "Lloyd McKenzie",
        "timestamp": 1593703494
    },
    {
        "content": "<p>Sorry about this- Should be back up momentarily :)</p>",
        "id": 202711088,
        "sender_full_name": "James Agnew",
        "timestamp": 1593707047
    }
]