[
    {
        "content": "<p>userSelected seems pretty useful if you have more than one coding. If you only have one, would this ever be needed? It seems it could distinguish inferred information, but you wouldn't know in adavnce, and it would mainly be used in the negative case.</p>",
        "id": 200154615,
        "sender_full_name": "Jay Lyle",
        "timestamp": 1591649611
    },
    {
        "content": "<p>it's not so useful in practice, but is still theoretically justified</p>",
        "id": 200157417,
        "sender_full_name": "Grahame Grieve",
        "timestamp": 1591651205
    },
    {
        "content": "<p>IMO, still handy to know that something was explicitly user selected. Even if there's only one coded concept, to know what it wasn't mapped/inferred is valuable.</p>",
        "id": 200240403,
        "sender_full_name": "Eric Whitley",
        "timestamp": 1591714492
    }
]