[
    {
        "content": "<p>lmckenzi <a href=\"https://github.com/HL7/fhir/commit/23442c23d356\" target=\"_blank\" title=\"https://github.com/HL7/fhir/commit/23442c23d356\">pushed</a> 1 commit to branch Fix-SD-invariants. Commits by Lloyd McKenzie (1).</p>\n<ul>\n<li><a href=\"http://gforge.hl7.org/gf/project/fhir/tracker/?action=TrackerItemEdit&amp;tracker_item_id=19762\" target=\"_blank\" title=\"http://gforge.hl7.org/gf/project/fhir/tracker/?action=TrackerItemEdit&amp;tracker_item_id=19762\">GF#19762</a> and fixed handling of replaceMatches (<a href=\"https://github.com/HL7/fhir/commit/23442c23d35695b1ae37fd2eb10328549e2fbc25\" target=\"_blank\" title=\"https://github.com/HL7/fhir/commit/23442c23d35695b1ae37fd2eb10328549e2fbc25\">23442c2</a>)</li>\n</ul>",
        "id": 154024732,
        "sender_full_name": "Github Notifications",
        "timestamp": 1544599205
    },
    {
        "content": "<p>lmckenzi <a href=\"https://github.com/HL7/fhir/compare/23442c23d356...000000000000\" target=\"_blank\" title=\"https://github.com/HL7/fhir/compare/23442c23d356...000000000000\">deleted</a> the branch Fix-SD-invariants.</p>",
        "id": 154024846,
        "sender_full_name": "Github Notifications",
        "timestamp": 1544630642
    }
]