[
    {
        "content": "<p>Hi - trying to comment last minute (as usual) . I am a little confused by the ballot rule statement, \"The specification has been updated to include R3/R4 maps and difference analysis, but these have not been updated\" \" as to whether or not I can rely on the AR and AB links to let me look only at the changes - if not, then how do I know what the commentable changes are?</p>",
        "id": 153999483,
        "sender_full_name": "Gay Dolin",
        "timestamp": 1537811350
    },
    {
        "content": "<p>the commentable changes are the differences between this ballot and the last ballot, not between R4 and R3.</p>",
        "id": 153999597,
        "sender_full_name": "Grahame Grieve",
        "timestamp": 1537824892
    },
    {
        "content": "<p>every page includes a link at the bottom to compare with the last ballot</p>",
        "id": 153999598,
        "sender_full_name": "Grahame Grieve",
        "timestamp": 1537824911
    },
    {
        "content": "<p>Thanks - figured it out :-)</p>",
        "id": 153999634,
        "sender_full_name": "Gay Dolin",
        "timestamp": 1537828615
    },
    {
        "content": "<p>hey all</p>",
        "id": 154010332,
        "sender_full_name": "Grahame Grieve",
        "timestamp": 1539918662
    },
    {
        "content": "<p>I'm back to pushing on this. Is anyone going to be interested in helping out with this in the next 2-3 weeks?</p>",
        "id": 154010333,
        "sender_full_name": "Grahame Grieve",
        "timestamp": 1539918684
    },
    {
        "content": "<p>Me and <span class=\"user-mention\" data-user-id=\"192710\">@Kenneth Myhra</span> are working on it</p>",
        "id": 154019334,
        "sender_full_name": "Vadim Peretokin",
        "timestamp": 1542432851
    },
    {
        "content": "<p>I know how to finish the 4 outstanding maps I've got and there's just 2 on the list now</p>",
        "id": 154022854,
        "sender_full_name": "Vadim Peretokin",
        "timestamp": 1543949510
    },
    {
        "content": "<p>I'll look into tackling them too</p>",
        "id": 154022855,
        "sender_full_name": "Vadim Peretokin",
        "timestamp": 1543949517
    },
    {
        "content": "<p>great thanks</p>",
        "id": 154022865,
        "sender_full_name": "Grahame Grieve",
        "timestamp": 1543952325
    }
]