[
    {
        "content": "<p>Can someone please let me know a roadmap to be FHIR-based eCQM developer?  Many thanks for your help.</p>\n<p>Regards,<br>\nTien Thai</p>",
        "id": 183390089,
        "sender_full_name": "Tien Thai",
        "timestamp": 1576264412
    },
    {
        "content": "<p>I don't think there's a formal roadmap.  <span class=\"user-mention\" data-user-id=\"191359\">@Bryn Rhodes</span> may have some recommendations though...</p>",
        "id": 183391686,
        "sender_full_name": "Lloyd McKenzie",
        "timestamp": 1576265315
    },
    {
        "content": "<p>We are working on some FHIR-based quality reporting educational sessions, stay tuned to the <a href=\"https://ecqi.healthit.gov/\" target=\"_blank\" title=\"https://ecqi.healthit.gov/\">eCQI Resource Center</a> for those events as they come up. We have also incorporated FHIR into the <a href=\"https://github.com/esacinc/CQL-Formatting-and-Usage-Wiki/wiki/Cooking-with-CQL-Examples\" target=\"_blank\" title=\"https://github.com/esacinc/CQL-Formatting-and-Usage-Wiki/wiki/Cooking-with-CQL-Examples\">Cooking with CQL</a> sessions.</p>",
        "id": 183405658,
        "sender_full_name": "Bryn Rhodes",
        "timestamp": 1576274662
    },
    {
        "content": "<p>If you have specific questions or examples you'd like to see worked through, we are always looking for Cooking with CQL examples.</p>",
        "id": 183405702,
        "sender_full_name": "Bryn Rhodes",
        "timestamp": 1576274686
    }
]