[
    {
        "content": "<p>For today's 3p ET meeting we'll take notes here. Please feel free to join in the discussion. <a href=\"https://join.freeconferencecall.com/fhir\" target=\"_blank\" title=\"https://join.freeconferencecall.com/fhir\">https://join.freeconferencecall.com/fhir</a> (meeting ID: FHIR)</p>\n<p>Key docs for our call: <a href=\"https://docs.google.com/spreadsheets/d/1LgfmqZLcEiprCDXrHCG9NyT4rG0wulN0gnwtd4wK1u8/edit#gid=0\" target=\"_blank\" title=\"https://docs.google.com/spreadsheets/d/1LgfmqZLcEiprCDXrHCG9NyT4rG0wulN0gnwtd4wK1u8/edit#gid=0\">Ballot Themes List</a> with prioritized issues in red at the bottom; and <a href=\"https://docs.google.com/spreadsheets/d/1j-Dp6B3VetJ_dMseTl6F9qu4GIZr5b9HFRB4iURfSLw/edit#gid=569200369\" target=\"_blank\" title=\"https://docs.google.com/spreadsheets/d/1j-Dp6B3VetJ_dMseTl6F9qu4GIZr5b9HFRB4iURfSLw/edit#gid=569200369\">Ballot Summary Spreadsheet</a> with full ballot comments + dispositions so far.</p>",
        "id": 153922304,
        "sender_full_name": "Josh Mandel",
        "timestamp": 1512057848
    },
    {
        "content": "<p>Attendees: <span class=\"user-mention\" data-user-id=\"191315\">@Josh Mandel</span> (leading) , <span class=\"user-mention\" data-user-id=\"191414\">@Dan Gottlieb</span> , <span class=\"user-mention\" data-user-id=\"192576\">@Robert Scanlon</span> ,  <span class=\"user-mention\" data-user-id=\"194155\">@Dylan Mahalingam</span> , <span class=\"user-mention\" data-user-id=\"192825\">@Jeffrey Danford</span> , Lisa Erickson, <span class=\"user-mention\" data-user-id=\"191864\">@Isaac Vetter</span>, <span class=\"user-mention\" data-user-id=\"191496\">@Nikolai Schwertner</span>, <span class=\"user-mention\" data-user-id=\"194712\">@Debbie Bucci</span>, <span class=\"user-mention\" data-user-id=\"191401\">@Eric Haas</span>, <span class=\"user-mention\" data-user-id=\"191316\">@Grahame Grieve</span>, Clark Downum</p>",
        "id": 153922339,
        "sender_full_name": "Isaac Vetter",
        "timestamp": 1512072450
    },
    {
        "content": "<p>Topic #1: \"Theme: Publication Format (103, 104, 110, 163, 179, 183)\"<br>\n - Topic consists of a a handful of comments focused on the actual formatting of the specification.</p>\n<p>Jeff - we shouldn't overly pollute the specification with inline examples.</p>\n<p>Jeff motions and Debbie seconds. PASS 8 (for), 0 (abstain), 0 (against)</p>",
        "id": 153922341,
        "sender_full_name": "Isaac Vetter",
        "timestamp": 1512072551
    },
    {
        "content": "<p>Topic #2: Links to versioned FHIR spec (71)</p>",
        "id": 153922342,
        "sender_full_name": "Isaac Vetter",
        "timestamp": 1512073114
    },
    {
        "content": "<p>Eric motions, Isaac seconds. PASS 9 (for), 0 (abstain), 0 (against)</p>",
        "id": 153922344,
        "sender_full_name": "Isaac Vetter",
        "timestamp": 1512073131
    },
    {
        "content": "<p>Topic #3: Separate out docs for Scopes vs. Launch Context ?(142)</p>",
        "id": 153922345,
        "sender_full_name": "Isaac Vetter",
        "timestamp": 1512073176
    },
    {
        "content": "<p>Eric - supports keeping the content together<br>\nIsaac - Much of the launch context content doesn't actually apply to scope and by making the page shorter, the spec is easier to read<br>\nIsaac motions, Nikolai seconds. PASS 0 (for), 0 (abstain),  0 (against)</p>",
        "id": 153922348,
        "sender_full_name": "Isaac Vetter",
        "timestamp": 1512073511
    },
    {
        "content": "<p>Topic #4: Presenting access duration details to user (207)</p>",
        "id": 153922349,
        "sender_full_name": "Isaac Vetter",
        "timestamp": 1512073577
    },
    {
        "content": "<p>Jeff - it seems like a nice feature and it's not a requirement</p>",
        "id": 153922351,
        "sender_full_name": "Isaac Vetter",
        "timestamp": 1512073800
    },
    {
        "content": "<p>Eric motions, Jeff seconds: against: 0, abstain:0, for: 9 - PASS</p>",
        "id": 153922352,
        "sender_full_name": "Isaac Vetter",
        "timestamp": 1512073884
    },
    {
        "content": "<p>Topic #5: Registering a SMART App with an EHR: Dynamic Ports (206)</p>",
        "id": 153922355,
        "sender_full_name": "Isaac Vetter",
        "timestamp": 1512074090
    },
    {
        "content": "<p>Isaac - shouldn't we account for mobile apps?<br>\nJosh - yes, how about we point out the exception for native apps?<br>\nIsaac, Clark - sounds great!</p>\n<p>Grahame motions, Isaac seconds. against: 0, abstain:0, for: 11 - PASS</p>",
        "id": 153922360,
        "sender_full_name": "Isaac Vetter",
        "timestamp": 1512074682
    },
    {
        "content": "<p>Topic #6: Backend Servicves (192)</p>",
        "id": 153922362,
        "sender_full_name": "Isaac Vetter",
        "timestamp": 1512074832
    },
    {
        "content": "<p>Josh - backend services is important, but not mature or widely implemented and therefore shouldn't be balloted</p>",
        "id": 153922364,
        "sender_full_name": "Isaac Vetter",
        "timestamp": 1512074856
    },
    {
        "content": "<p>Josh - the backend services spec should be matured via FHIR Connectathons, the mailing list and zulip</p>",
        "id": 153922367,
        "sender_full_name": "Isaac Vetter",
        "timestamp": 1512074892
    },
    {
        "content": "<p>Grahame - how about the spec mentions that it's something we're working on?<br>\nJosh, Isaac: okay.</p>",
        "id": 153922369,
        "sender_full_name": "Isaac Vetter",
        "timestamp": 1512074924
    },
    {
        "content": "<p>Isaac motions, Grahame seconds: against: 0, abstain:0, for: 11 - PASS</p>",
        "id": 153922371,
        "sender_full_name": "Isaac Vetter",
        "timestamp": 1512075006
    },
    {
        "content": "<p>Topic #7: Three parties, or four parties?<br>\nJosh - not sure that we understand the comment. <br>\nGrahame- perhaps he's asking about security between the user and browser -- the potential for data breach between multiple users on the same platform?<br>\nJosh - I'll reach out to commenter to clarify or join next call</p>",
        "id": 153922374,
        "sender_full_name": "Isaac Vetter",
        "timestamp": 1512075295
    },
    {
        "content": "<p>Topic #8: Scopes and Scopes (186)</p>",
        "id": 153922375,
        "sender_full_name": "Isaac Vetter",
        "timestamp": 1512075306
    },
    {
        "content": "<p>Isaac - I haven't been confused between the two meaning of \"launch scope\" and \"in scope\"<br>\nGrahame - it seems unavoidable ...<br>\nEric motions, Jeff seconds: against: 0, abstain:0, for: 10 - PASS</p>",
        "id": 153922377,
        "sender_full_name": "Isaac Vetter",
        "timestamp": 1512075478
    }
]