[
    {
        "content": "<p><span class=\"user-mention\" data-user-id=\"191319\">@James Agnew</span> my code is all confused about FHIRException - we have version specific and Version independent ones of this. Which should we have? can we have just one?</p>",
        "id": 153844091,
        "sender_full_name": "Grahame Grieve",
        "timestamp": 1471468407
    },
    {
        "content": "<p>Yeah, we really should just have one I'd agree. This seems like something that should be version independant.</p>",
        "id": 153845232,
        "sender_full_name": "James Agnew",
        "timestamp": 1472210888
    }
]