[
    {
        "content": "<p>Hi <span class=\"user-mention\" data-user-id=\"191469\">@Chris Moesel</span> ,</p>\n<p>I am wondering why the JSON files within this tool do not follow the standard for FHIR resources. This is the tool I am referring to: <br>\n<a href=\"https://github.com/AHRQ-CDS/AHRQ-CDS-Connect-PAIN-MANAGEMENT-SUMMARY/tree/master/src\">https://github.com/AHRQ-CDS/AHRQ-CDS-Connect-PAIN-MANAGEMENT-SUMMARY/tree/master/src</a></p>\n<p><span class=\"user-mention\" data-user-id=\"193795\">@Joel Francis</span> <span class=\"user-mention\" data-user-id=\"192545\">@Alex Goel</span> </p>\n<p>Thank you,<br>\nChrista</p>",
        "id": 237700120,
        "sender_full_name": "Christa Wan",
        "timestamp": 1620323192
    },
    {
        "content": "<p>Which specific JSON files are you referring to?  There are</p>\n<ul>\n<li>ELM JSON files, which are not intended to be FHIR resources</li>\n<li>valueset-db.json, which is an internal value set cache format (but I suppose <em>could</em> have been represented as a FHIR bundle of value sets)</li>\n<li>FHIR bundles for test patients (which <em>should</em> be standard FHIR resources)</li>\n</ul>",
        "id": 237714590,
        "sender_full_name": "Chris Moesel",
        "timestamp": 1620328838
    }
]